azure/mgmt/kubernetesconfiguration/extensions/__init__.py
azure/mgmt/kubernetesconfiguration/extensions/_configuration.py
azure/mgmt/kubernetesconfiguration/extensions/_kubernetes_configuration_extensions_mgmt_client.py
azure/mgmt/kubernetesconfiguration/extensions/_patch.py
azure/mgmt/kubernetesconfiguration/extensions/_version.py
azure/mgmt/kubernetesconfiguration/extensions/py.typed
azure/mgmt/kubernetesconfiguration/extensions/_utils/__init__.py
azure/mgmt/kubernetesconfiguration/extensions/_utils/serialization.py
azure/mgmt/kubernetesconfiguration/extensions/aio/__init__.py
azure/mgmt/kubernetesconfiguration/extensions/aio/_configuration.py
azure/mgmt/kubernetesconfiguration/extensions/aio/_kubernetes_configuration_extensions_mgmt_client.py
azure/mgmt/kubernetesconfiguration/extensions/aio/_patch.py
azure/mgmt/kubernetesconfiguration/extensions/aio/operations/__init__.py
azure/mgmt/kubernetesconfiguration/extensions/aio/operations/_extensions_operations.py
azure/mgmt/kubernetesconfiguration/extensions/aio/operations/_operation_status_operations.py
azure/mgmt/kubernetesconfiguration/extensions/aio/operations/_patch.py
azure/mgmt/kubernetesconfiguration/extensions/models/__init__.py
azure/mgmt/kubernetesconfiguration/extensions/models/_kubernetes_configuration_extensions_mgmt_client_enums.py
azure/mgmt/kubernetesconfiguration/extensions/models/_models_py3.py
azure/mgmt/kubernetesconfiguration/extensions/models/_patch.py
azure/mgmt/kubernetesconfiguration/extensions/operations/__init__.py
azure/mgmt/kubernetesconfiguration/extensions/operations/_extensions_operations.py
azure/mgmt/kubernetesconfiguration/extensions/operations/_operation_status_operations.py
azure/mgmt/kubernetesconfiguration/extensions/operations/_patch.py
azure_mgmt_kubernetesconfiguration_extensions-1.0.0b1.dist-info/LICENSE
azure_mgmt_kubernetesconfiguration_extensions-1.0.0b1.dist-info/METADATA
azure_mgmt_kubernetesconfiguration_extensions-1.0.0b1.dist-info/WHEEL
azure_mgmt_kubernetesconfiguration_extensions-1.0.0b1.dist-info/top_level.txt
azure_mgmt_kubernetesconfiguration_extensions-1.0.0b1.dist-info/RECORD
